janus/__init__.py
janus/py.typed
janus-0.7.0.dist-info/METADATA
janus-0.7.0.dist-info/WHEEL
janus-0.7.0.dist-info/top_level.txt
janus-0.7.0.dist-info/zip-safe
janus-0.7.0.dist-info/RECORD
