Metadata-Version: 2.1
Name: janus
Version: 0.7.0
Summary: Mixed sync-async queue to interoperate between asyncio tasks and classic threads
Home-page: https://github.com/aio-libs/janus
Author: Andrew Svetlov <andrew.svetlov@gmail.com>
Author-email: andrew.svetlov@gmail.com
License: Apache 2
Project-URL: Chat: Gitter, https://gitter.im/aio-libs/Lobby
Project-URL: CI: GitHub Actions, https://github.com/aio-libs/janus/actions/workflows/ci.yml
Project-URL: Coverage: codecov, https://codecov.io/github/aio-libs/janus
Project-URL: GitHub: issues, https://github.com/aio-libs/janus/issues
Project-URL: GitHub: repo, https://github.com/aio-libs/janus
Keywords: janus,queue,asyncio
Platform: UNKNOWN
Classifier: Development Status :: 5 - Production/Stable
Classifier: Framework :: AsyncIO
Classifier: Intended Audience :: Developers
Classifier: License :: OSI Approved :: Apache Software License
Classifier: Operating System :: POSIX
Classifier: Operating System :: MacOS :: MacOS X
Classifier: Operating System :: Microsoft :: Windows
Classifier: Programming Language :: Python
Classifier: Programming Language :: Python :: 3
Classifier: Programming Language :: Python :: 3.6
Classifier: Programming Language :: Python :: 3.7
Classifier: Programming Language :: Python :: 3.8
Classifier: Programming Language :: Python :: 3.9
Classifier: Programming Language :: Python :: 3.10
Classifier: Topic :: Software Development :: Libraries
Requires-Python: >=3.6
Requires-Dist: typing-extensions (>=3.7.4.3)
